{"stats":{"minecraft:mined":{"minecraft:white_wall_banner":2},"minecraft:used":{"minecraft:chest":26,"minecraft:stone_bricks":1,"minecraft:furnace":1,"minecraft:crafting_table":1,"minecraft:deepslate":1,"alexsmobs:animal_dictionary":1},"minecraft:dropped":{"minecraft:spruce_sign":3,"minecraft:enchanted_book":1,"minecraft:bread":192,"iceandfire:lightning_dragon_blood":9,"iceandfire:dragonarmor_diamond_head":1,"iceandfire:dragonscales_sapphire":17,"iceandfire:dragonarmor_diamond_body":1,"minecraft:vine":9,"minecraft:moss_block":55,"minecraft:wheat_seeds":129,"iceandfire:armor_gray_boots":1,"minecraft:oak_log":21,"minecraft:cooked_beef":18,"minecraft:baked_potato":2,"minecraft:lilac":1,"minecraft:glow_ink_sac":68,"iceandfire:armor_white_helmet":1,"minecraft:spore_blossom":2,"minecraft:crafting_table":2,"alexsmobs:kangaroo_meat":5,"minecraft:crossbow":2,"minecraft:mangrove_propagule":1,"minecraft:cobblestone":18,"minecraft:cookie":5,"minecraft:iron_helmet":1,"minecraft:glow_berries":87,"iceandfire:ice_dragon_flesh":10,"iceandfire:fire_dragon_flesh":64,"iceandfire:dragon_stick":2,"minecraft:leather":64,"travelersbackpack:blue_sleeping_bag":4,"travelersbackpack:purple_sleeping_bag":5,"travelersbackpack:iron_tier_upgrade":1,"minecraft:iron_horse_armor":1,"minecraft:saddle":2,"minecraft:tropical_fish":2,"minecraft:acacia_log":8,"travelersbackpack:standard":5,"minecraft:coal":64,"minecraft:leather_helmet":1,"minecraft:golden_apple":10,"minecraft:stick":54,"minecraft:cod":5,"iceandfire:dragon_flute":2,"minecraft:cobweb":64,"minecraft:grass":6,"minecraft:dark_oak_log":94,"minecraft:large_fern":2,"minecraft:cornflower":1,"iceandfire:silver_sword":2,"iceandfire:lightning_lily":2,"minecraft:mutton":64,"iceandfire:dragon_horn":2,"minecraft:iron_leggings":4,"minecraft:jungle_sapling":1,"minecraft:pumpkin":20,"iceandfire:armor_white_leggings":1,"minecraft:pumpkin_pie":4,"iceandfire:ice_dragon_heart":2,"minecraft:wither_rose":1,"minecraft:flowering_azalea":8,"minecraft:white_banner":2,"iceandfire:fire_dragon_blood":7,"minecraft:sugar":5,"minecraft:iron_pickaxe":1,"minecraft:cactus":1,"minecraft:iron_shovel":1,"minecraft:string":128,"travelersbackpack:backpack_tank":18,"minecraft:bucket":6,"iceandfire:armor_gray_helmet":1,"iceandfire:dragon_skull_fire":13,"iceandfire:dragonscales_bronze":64,"minecraft:bone":64,"iceandfire:armor_white_chestplate":1,"minecraft:dandelion":3,"iceandfire:dragonbone":16,"minecraft:dark_oak_door":4,"minecraft:furnace":1,"minecraft:moss_carpet":64,"minecraft:sweet_berries":81,"minecraft:sugar_cane":59,"minecraft:cooked_chicken":1,"iceandfire:lightning_dragon_heart":1,"alexsmobs:animal_dictionary":1,"minecraft:cobbled_deepslate":48,"iceandfire:armor_white_boots":1,"minecraft:cocoa_beans":12,"minecraft:bowl":14,"minecraft:birch_sapling":3,"minecraft:beetroot":2,"minecraft:experience_bottle":1,"minecraft:stripped_dark_oak_log":39,"minecraft:cherry_sapling":1,"minecraft:chicken":20,"minecraft:rotten_flesh":51,"minecraft:enchanted_golden_apple":1,"minecraft:iron_boots":2,"minecraft:clay_ball":3,"iceandfire:hydra_fang":12,"minecraft:fern":4,"iceandfire:fire_lily":2,"iceandfire:dragon_skull_ice":4,"iceandfire:troll_tusk":8,"iceandfire:myrmex_jungle_resin":72,"minecraft:honey_bottle":4,"alexsmobs:emu_egg":3,"minecraft:salmon":22,"iceandfire:shiny_scales":7,"iceandfire:armor_gray_leggings":1,"minecraft:poppy":2,"minecraft:rabbit_hide":12,"minecraft:potato":128,"minecraft:hay_block":85,"minecraft:tipped_arrow":6,"minecraft:stone":1,"minecraft:shield":2,"minecraft:flower_pot":1,"minecraft:mangrove_log":15,"minecraft:gunpowder":64,"iceandfire:armor_gray_chestplate":1,"minecraft:skeleton_skull":5,"travelersbackpack:iron_golem":1,"minecraft:iron_chestplate":2,"minecraft:jungle_log":9,"minecraft:ladder":4,"minecraft:andesite":5,"minecraft:cod_bucket":2,"minecraft:melon_seeds":24,"minecraft:leather_boots":2,"minecraft:acacia_sapling":11,"minecraft:azalea":9,"iceandfire:dragonarmor_diamond_tail":1,"minecraft:chest":65,"iceandfire:dragon_meal":64,"iceandfire:frost_lily":2,"minecraft:leather_leggings":3,"minecraft:spider_eye":3,"minecraft:bamboo":2,"minecraft:spruce_log":128,"minecraft:beef":64,"iceandfire:fire_dragon_heart":5,"minecraft:arrow":116,"minecraft:bow":1,"minecraft:stone_pickaxe":1,"iceandfire:ice_dragon_blood":4,"alexsmobs:banana":3,"iceandfire:dragonarmor_diamond_neck":1,"iceandfire:dragon_skull_lightning":4,"minecraft:egg":32},"minecraft:crafted":{"travelersbackpack:standard":9},"minecraft:custom":{"minecraft:interact_with_crafting_table":3,"minecraft:leave_game":2,"minecraft:time_since_death":78376,"minecraft:sprint_one_cm":8942,"minecraft:walk_one_cm":12563,"minecraft:drop":216,"minecraft:play_time":78376,"minecraft:jump":78,"minecraft:total_world_time":78376,"minecraft:interact_with_furnace":1,"minecraft:time_since_rest":78376,"minecraft:damage_taken":240,"minecraft:fly_one_cm":15202,"minecraft:open_chest":37,"minecraft:fall_one_cm":5640},"minecraft:picked_up":{"iceandfire:dragon_skull_lightning":2,"minecraft:cocoa_beans":12,"minecraft:iron_chestplate":2,"minecraft:crafting_table":2,"minecraft:ladder":4,"minecraft:chicken":20,"minecraft:clay_ball":3,"minecraft:flower_pot":1,"iceandfire:fire_lily":2,"minecraft:leather_leggings":3,"minecraft:wither_rose":1,"minecraft:enchanted_book":1,"iceandfire:armor_gray_leggings":1,"minecraft:shield":2,"iceandfire:armor_gray_helmet":1,"minecraft:cod_bucket":2,"minecraft:cornflower":1,"minecraft:string":128,"minecraft:moss_carpet":64,"minecraft:large_fern":2,"minecraft:iron_leggings":4,"minecraft:iron_shovel":1,"minecraft:experience_bottle":1,"minecraft:beetroot":2,"minecraft:cobbled_deepslate":48,"alexsmobs:banana":3,"minecraft:bucket":6,"iceandfire:hydra_fang":12,"iceandfire:frost_lily":2,"minecraft:jungle_sapling":1,"minecraft:azalea":9,"minecraft:poppy":2,"minecraft:iron_pickaxe":1,"minecraft:mangrove_log":15,"minecraft:sugar_cane":59,"minecraft:enchanted_golden_apple":1,"minecraft:chest":65,"minecraft:birch_sapling":3,"minecraft:egg":32,"minecraft:iron_boots":2,"iceandfire:ice_dragon_heart":2,"minecraft:furnace":1,"minecraft:dark_oak_door":4,"minecraft:tipped_arrow":6,"minecraft:stick":54,"iceandfire:dragonbone":16,"minecraft:stone":1,"iceandfire:troll_tusk":8,"minecraft:acacia_log":8,"iceandfire:dragonarmor_diamond_neck":1,"minecraft:bowl":14,"travelersbackpack:iron_tier_upgrade":1,"iceandfire:dragonarmor_diamond_tail":1,"minecraft:cookie":5,"iceandfire:lightning_dragon_blood":9,"minecraft:vine":9,"iceandfire:dragonarmor_diamond_head":1,"minecraft:iron_horse_armor":1,"iceandfire:dragon_skull_ice":2,"iceandfire:lightning_lily":2,"minecraft:cactus":1,"minecraft:arrow":116,"minecraft:honey_bottle":4,"minecraft:rotten_flesh":51,"minecraft:pumpkin_pie":4,"minecraft:hay_block":85,"iceandfire:fire_dragon_heart":5,"alexsmobs:emu_egg":3,"minecraft:saddle":2,"alexsmobs:kangaroo_meat":5,"minecraft:glow_berries":87,"minecraft:cod":5,"minecraft:mutton":64,"minecraft:skeleton_skull":5,"minecraft:cobblestone":18,"travelersbackpack:iron_golem":1,"minecraft:cooked_beef":18,"minecraft:lilac":1,"minecraft:jungle_log":9,"minecraft:andesite":5,"minecraft:glow_ink_sac":68,"minecraft:salmon":22,"minecraft:leather":64,"minecraft:fern":4,"minecraft:potato":128,"minecraft:oak_log":21,"minecraft:gunpowder":64,"iceandfire:dragonscales_bronze":64,"minecraft:white_banner":4,"iceandfire:dragonarmor_diamond_body":1,"minecraft:leather_boots":2,"iceandfire:ice_dragon_blood":4,"minecraft:bone":64,"travelersbackpack:backpack_tank":18,"iceandfire:armor_gray_boots":1,"iceandfire:myrmex_jungle_resin":72,"minecraft:bow":1,"minecraft:wheat_seeds":129,"iceandfire:dragon_stick":2,"minecraft:rabbit_hide":12,"minecraft:spore_blossom":2,"minecraft:stone_pickaxe":1,"iceandfire:armor_white_leggings":1,"iceandfire:armor_gray_chestplate":1,"minecraft:cooked_chicken":1,"minecraft:cobweb":64,"iceandfire:dragon_meal":64,"iceandfire:armor_white_helmet":1,"iceandfire:armor_white_boots":1,"minecraft:bamboo":2,"minecraft:moss_block":55,"iceandfire:fire_dragon_flesh":64,"minecraft:flowering_azalea":8,"minecraft:acacia_sapling":11,"iceandfire:dragon_horn":2,"minecraft:pumpkin":20,"minecraft:sweet_berries":81,"iceandfire:dragonscales_sapphire":17,"minecraft:dandelion":3,"iceandfire:dragon_skull_fire":6,"iceandfire:shiny_scales":7,"travelersbackpack:blue_sleeping_bag":4,"minecraft:dark_oak_log":94,"minecraft:spruce_log":128,"travelersbackpack:purple_sleeping_bag":5,"minecraft:spider_eye":3,"alexsmobs:animal_dictionary":1,"minecraft:leather_helmet":1,"travelersbackpack:standard":5,"iceandfire:dragon_flute":2,"minecraft:sugar":5,"iceandfire:fire_dragon_blood":7,"iceandfire:silver_sword":2,"iceandfire:armor_white_chestplate":1,"minecraft:iron_helmet":1,"minecraft:crossbow":2,"minecraft:grass":6,"minecraft:cherry_sapling":1,"minecraft:spruce_sign":3,"iceandfire:ice_dragon_flesh":10,"minecraft:bread":192,"minecraft:baked_potato":2,"minecraft:melon_seeds":24,"minecraft:stripped_dark_oak_log":39,"minecraft:mangrove_propagule":1,"minecraft:coal":64}},"DataVersion":3465}